alu_.sv
module alu_(
    input   logic [31:0]      ALUop1, 
    input logic [31:0] ALUop2,
    input   logic [2:0]            ALUctrl,
    output  logic [31:0]       ALUout,
    output  logic               EQ

);


always_comb begin
    case (ALUctrl)
    3'b000:     ALUout = ALUop1 + ALUop2;
    3'b001: ALUout = 32'b0;
    3'b010: ALUout = 32'b0;
    3'b011: ALUout = 32'b0;
    3'b100: ALUout = 32'b0;
    3'b101: ALUout = 32'b0;
    3'b110: ALUout = 32'b0;
    default:    ALUout = 0;
    endcase
end

assign      EQ = (ALUop1 == ALUop2);
    

endmodule

Reg_file.sv
module Reg_file #(
    parameter ADDRESS_WIDTH = 5,
              DATA_WIDTH = 32
)(
    input   logic [ADDRESS_WIDTH-1:0]        AD1,
    input   logic [ADDRESS_WIDTH-1:0]        AD2,
    input   logic [ADDRESS_WIDTH-1:0]        AD3,
    input   logic                            WE3,
    input   logic [DATA_WIDTH-1:0]           WD3,
    input   logic                            clk,
    output  logic [DATA_WIDTH-1:0]           RD1,
    output  logic [DATA_WIDTH-1:0]           RD2,
    output  logic [DATA_WIDTH-1:0]           a0

);

    logic [DATA_WIDTH-1:0] reg_array [2**ADDRESS_WIDTH-1:0];

    always_ff @ (posedge clk) begin
        if (WE3)
            reg_array[AD3] <= WD3;
    end 

    assign a0 = reg_array[{5'b01010}];

    always_comb
    begin
        RD1 = reg_array[AD1];
        RD2 = reg_array[AD2];
    end

     initial begin
        for (int i = 0; i < $size(reg_array); i++) begin
            reg_array[i] = 32'b0;
        end
    end
        
endmodule

ALU.sv
module ALU #(
    parameter A_WIDTH = 5,
              D_WIDTH = 32  
)(
    // interface signals
    input logic               clk, 
    input logic               ALUsrc, 
    input logic [2:0]         ALUctrl, 
    input logic [31:0]          ImmOp, 
    input logic               WE3,  
    input logic [A_WIDTH-1:0] AD1, 
    input logic [A_WIDTH-1:0] AD2,
    input logic [A_WIDTH-1:0] AD3,
    output logic              EQ,
    output logic [D_WIDTH-1:0] a0
);

    logic [D_WIDTH-1:0] regOp2; 
    logic [D_WIDTH-1:0] ALUop1; 
    logic [D_WIDTH-1:0] ALUop2; 
    logic [D_WIDTH-1:0] ALUout; 

Reg_file regfile(
    .clk (clk),
    .AD1 (AD1),
    .AD2 (AD2),
    .AD3 (AD3),
    .WE3 (WE3),
    .RD1 (ALUop1),
    .RD2 (regOp2),
    .WD3 (ALUout),
    .a0 (a0)
);


  assign ALUop2 = ALUsrc ?  ImmOp : regOp2;


alu_ addralu (
    .ALUop1 (ALUop1),
    .ALUop2 (ALUop2),
    .EQ  (EQ),
    .ALUctrl (ALUctrl),
    .ALUout (ALUout)
);



endmodule

ControlUnit.sv

module ControlUnit #(
    parameter   DATA_WIDTH = 32
)(
    /* verilator lint_off UNUSED */
    input  logic [DATA_WIDTH-1:0]  instr,
    /* verilator lint_on UNUSED */
    input  logic                   EQ,
    output logic                   RegWrite,
    output logic [2:0]             ALUctrl,
    output logic                   ALUsrc,
    output logic [2:0]             ImmSrc,
    output logic                   PCsrc
);

logic [6:0] opcode;
logic [2:0] funct3;
//logic [6:0] funct7;

assign opcode = instr[6:0];
assign funct3 = instr[14:12];
// assign funct7 = instr[31:25]; 
    


always_comb
    case (opcode)
        7'b0010011: 
        begin 
            case (funct3) //addi
                3'b000: 
                begin
                    ALUctrl = 3'b000;
                    ALUsrc = 1'b1;
                    RegWrite = 1'b1;
                    ImmSrc = 3'b000;
                    PCsrc = 1'b0;
                end 
                default: 
                begin
                    RegWrite = 1'b0;
                    ALUctrl = 3'b000;
                    ALUsrc = 1'b0;
                    ImmSrc = 3'b000;
                    PCsrc = 1'b0;
                end 
            endcase
        end     
        7'b1100011: 
        begin
                 ImmSrc = 3'b001; //bne
                 RegWrite = 1'b0;
                 ALUctrl = 3'b000;
                 ALUsrc = 1'b0;
            case (funct3)
                3'b001:
                begin 
                    case (EQ)
                        0: 
                        begin
                           PCsrc = 1'b1;
                        end 
                        1: 
                        begin
                           PCsrc = 1'b0;
                        end
                        default: 
                        begin
                            PCsrc = 1'b1;
                        end
                    endcase
                end 
                default: 
                begin
                    RegWrite = 1'b0;
                    ALUctrl = 3'b000;
                    ALUsrc = 1'b0;
                    ImmSrc = 3'b000;
                    PCsrc = 1'b0;
                end
            endcase
        end 
        default: 
        begin
            RegWrite = 1'b0;
            ALUctrl = 3'b000;
            ALUsrc = 1'b0;
            ImmSrc = 3'b000;
            PCsrc = 1'b0;
        end 
    endcase
                
endmodule

PC_Reg.sv
module PC_Reg (
    input logic [31:0]            next_PC,
    input logic                   rst,
    input logic                   clk, 
    output logic [31:0]           PC
);


always_ff @ (posedge clk, posedge rst)begin
   if(rst) PC <= {32'b0};
    else    PC <= next_PC;
end 

endmodule

toppc.sv
module toppc (          
  input logic  [31:0]      ImmOp,
  input logic              rst,   
  input logic              PCsrc,
  input logic              clk,
  output logic  [31:0]     PC
);
  

logic [31:0]  inc_PC;
logic [31:0]  branch_PC;
logic [31:0]  next_PC;
assign inc_PC = PC+4;
assign branch_PC = PC + ImmOp;

assign next_PC = PCsrc ? branch_PC : inc_PC;

PC_Reg  PC_Reg( 
  .rst (rst),
  .next_PC (next_PC),
  .clk (clk),
  .PC (PC)
);

endmodule

SignEx.sv
module SignEx (
    input  logic [2:0] ImmSrc,
    /* verilator lint_off UNUSED */
    input  logic [31:0] instr,
    /* verilator lint_on UNUSED */
    output logic [31:0] ImmOp
);


//logic [:]  _unused;


always_comb
    case(ImmSrc)
        000: ImmOp = {{20{instr[31]}}, instr[31:20]}; //addi
        001: ImmOp = {{20{instr[31]}}, instr[7],instr[30:25],instr[11:8],  1'b0}; //bne
        default: ImmOp = 32'b0;
    endcase 
    

endmodule

InstrMem.sv
module InstrMem #(
    parameter   ADDRESS_WIDTH = 32
)(
    input  logic  [ADDRESS_WIDTH-1:0]  addr,
    output logic  [ADDRESS_WIDTH-1:0]     instr
);

logic [7:0] rom_array [(2**14)-1:0];

initial begin
        $display("Loading rom.");
        $readmemh("Lab4.mem", rom_array);
end;

always_comb begin
    instr = {{rom_array [addr+0]}, {rom_array [addr+1]}, {rom_array [addr+2]}, {rom_array[addr+3]}};
end 
endmodule

cpu.sv
module cpu #(
    parameter A_WIDTH = 32
)(
    //interface signals
    input logic clk, 
    input logic rst, 
    output logic [31:0] a0
);

    //connecting wires
logic [A_WIDTH-1:0] PC; 
logic [A_WIDTH-1:0] instr; 
logic PCsrc;
logic [2:0] ALUctrl; 
logic ALUsrc; 
logic EQ; 
logic regwrite; 
logic [2:0] Immsrc; 
logic [31:0] Immop; 
logic [4:0] rs1; 
logic [4:0] rs2; 
logic [4:0] rd; 


assign rs1 = instr[19:15];
assign rs2 = instr[24:20];
assign rd = instr[11:7]; 

InstrMem memory(
    .addr (PC),
    .instr (instr)
);

SignEx immext(
    .ImmOp (Immop), 
    .ImmSrc (Immsrc),
    .instr(instr)
);

toppc pc (
    .clk (clk), 
    .rst (rst),
    .PC (PC),  
    .PCsrc (PCsrc),
    .ImmOp (Immop)
);

ControlUnit controlunit (
    .PCsrc (PCsrc), 
    .RegWrite (regwrite), 
    .ALUctrl (ALUctrl),
    .ALUsrc (ALUsrc), 
    .ImmSrc (Immsrc), 
    .EQ (EQ), 
    .instr (instr)
);

ALU alublock(
    .AD1 (rs1), 
    .AD2 (rs2), 
    .AD3 (rd),
    .WE3 (regwrite),
    .clk (clk), 
    .EQ (EQ), 
    .ALUctrl (ALUctrl),
    .ALUsrc (ALUsrc),
    .ImmOp (Immop), 
    .a0 (a0)
);

//secondtry

endmodule

cpu.vcd
$version Generated by VerilatedVcd $end
$date Sat Dec  3 16:58:41 2022 $end
$timescale 1ps $end

 $scope module TOP $end
  $var wire 32 V a0 [31:0] $end
  $var wire  1 T clk $end
  $var wire  1 U rst $end
  $scope module cpu $end
   $var wire  3 F ALUctrl [2:0] $end
   $var wire  1 G ALUsrc $end
   $var wire 32 \ A_WIDTH [31:0] $end
   $var wire  1 H EQ $end
   $var wire 32 K Immop [31:0] $end
   $var wire  3 J Immsrc [2:0] $end
   $var wire 32 W PC [31:0] $end
   $var wire  1 E PCsrc $end
   $var wire 32 V a0 [31:0] $end
   $var wire  1 T clk $end
   $var wire 32 D instr [31:0] $end
   $var wire  5 N rd [4:0] $end
   $var wire  1 I regwrite $end
   $var wire  5 L rs1 [4:0] $end
   $var wire  5 M rs2 [4:0] $end
   $var wire  1 U rst $end
   $scope module alublock $end
    $var wire  5 L AD1 [4:0] $end
    $var wire  5 M AD2 [4:0] $end
    $var wire  5 N AD3 [4:0] $end
    $var wire  3 F ALUctrl [2:0] $end
    $var wire 32 O ALUop1 [31:0] $end
    $var wire 32 P ALUop2 [31:0] $end
    $var wire 32 Q ALUout [31:0] $end
    $var wire  1 G ALUsrc $end
    $var wire 32 ] A_WIDTH [31:0] $end
    $var wire 32 \ D_WIDTH [31:0] $end
    $var wire  1 H EQ $end
    $var wire 32 K ImmOp [31:0] $end
    $var wire  1 I WE3 $end
    $var wire 32 V a0 [31:0] $end
    $var wire  1 T clk $end
    $var wire 32 X regOp2 [31:0] $end
    $scope module addralu $end
     $var wire  3 F ALUctrl [2:0] $end
     $var wire 32 O ALUop1 [31:0] $end
     $var wire 32 P ALUop2 [31:0] $end
     $var wire 32 Q ALUout [31:0] $end
     $var wire  1 H EQ $end
    $upscope $end
    $scope module regfile $end
     $var wire  5 L AD1 [4:0] $end
     $var wire  5 M AD2 [4:0] $end
     $var wire  5 N AD3 [4:0] $end
     $var wire 32 ] ADDRESS_WIDTH [31:0] $end
     $var wire 32 \ DATA_WIDTH [31:0] $end
     $var wire 32 O RD1 [31:0] $end
     $var wire 32 X RD2 [31:0] $end
     $var wire 32 Q WD3 [31:0] $end
     $var wire  1 I WE3 $end
     $var wire 32 V a0 [31:0] $end
     $var wire  1 T clk $end
     $var wire 32 $ reg_array[0] [31:0] $end
     $var wire 32 . reg_array[10] [31:0] $end
     $var wire 32 / reg_array[11] [31:0] $end
     $var wire 32 0 reg_array[12] [31:0] $end
     $var wire 32 1 reg_array[13] [31:0] $end
     $var wire 32 2 reg_array[14] [31:0] $end
     $var wire 32 3 reg_array[15] [31:0] $end
     $var wire 32 4 reg_array[16] [31:0] $end
     $var wire 32 5 reg_array[17] [31:0] $end
     $var wire 32 6 reg_array[18] [31:0] $end
     $var wire 32 7 reg_array[19] [31:0] $end
     $var wire 32 % reg_array[1] [31:0] $end
     $var wire 32 8 reg_array[20] [31:0] $end
     $var wire 32 9 reg_array[21] [31:0] $end
     $var wire 32 : reg_array[22] [31:0] $end
     $var wire 32 ; reg_array[23] [31:0] $end
     $var wire 32 < reg_array[24] [31:0] $end
     $var wire 32 = reg_array[25] [31:0] $end
     $var wire 32 > reg_array[26] [31:0] $end
     $var wire 32 ? reg_array[27] [31:0] $end
     $var wire 32 @ reg_array[28] [31:0] $end
     $var wire 32 A reg_array[29] [31:0] $end
     $var wire 32 & reg_array[2] [31:0] $end
     $var wire 32 B reg_array[30] [31:0] $end
     $var wire 32 C reg_array[31] [31:0] $end
     $var wire 32 ' reg_array[3] [31:0] $end
     $var wire 32 ( reg_array[4] [31:0] $end
     $var wire 32 ) reg_array[5] [31:0] $end
     $var wire 32 * reg_array[6] [31:0] $end
     $var wire 32 + reg_array[7] [31:0] $end
     $var wire 32 , reg_array[8] [31:0] $end
     $var wire 32 - reg_array[9] [31:0] $end
     $scope module unnamedblk1 $end
      $var wire 32 # i [31:0] $end
     $upscope $end
    $upscope $end
   $upscope $end
   $scope module controlunit $end
    $var wire  3 F ALUctrl [2:0] $end
    $var wire  1 G ALUsrc $end
    $var wire 32 \ DATA_WIDTH [31:0] $end
    $var wire  1 H EQ $end
    $var wire  3 J ImmSrc [2:0] $end
    $var wire  1 E PCsrc $end
    $var wire  1 I RegWrite $end
    $var wire  3 S funct3 [2:0] $end
    $var wire 32 D instr [31:0] $end
    $var wire  7 R opcode [6:0] $end
   $upscope $end
   $scope module immext $end
    $var wire 32 K ImmOp [31:0] $end
    $var wire  3 J ImmSrc [2:0] $end
    $var wire 32 D instr [31:0] $end
   $upscope $end
   $scope module memory $end
    $var wire 32 \ ADDRESS_WIDTH [31:0] $end
    $var wire 32 W addr [31:0] $end
    $var wire 32 D instr [31:0] $end
   $upscope $end
   $scope module pc $end
    $var wire 32 K ImmOp [31:0] $end
    $var wire 32 W PC [31:0] $end
    $var wire  1 E PCsrc $end
    $var wire 32 Z branch_PC [31:0] $end
    $var wire  1 T clk $end
    $var wire 32 Y inc_PC [31:0] $end
    $var wire 32 [ next_PC [31:0] $end
    $var wire  1 U rst $end
    $scope module PC_Reg $end
     $var wire 32 W PC [31:0] $end
     $var wire  1 T clk $end
     $var wire 32 [ next_PC [31:0] $end
     $var wire  1 U rst $end
    $upscope $end
   $upscope $end
  $upscope $end
 $upscope $end
$enddefinitions $end


#0
b00000000000000000000000000000000 #
b00000000000000000000000000000000 $
b00000000000000000000000000000000 %
b00000000000000000000000000000000 &
b00000000000000000000000000000000 '
b00000000000000000000000000000000 (
b00000000000000000000000000000000 )
b00000000000000000000000000000000 *
b00000000000000000000000000000000 +
b00000000000000000000000000000000 ,
b00000000000000000000000000000000 -
b00000000000000000000000000000000 .
b00000000000000000000000000000000 /
b00000000000000000000000000000000 0
b00000000000000000000000000000000 1
b00000000000000000000000000000000 2
b00000000000000000000000000000000 3
b00000000000000000000000000000000 4
b00000000000000000000000000000000 5
b00000000000000000000000000000000 6
b00000000000000000000000000000000 7
b00000000000000000000000000000000 8
b00000000000000000000000000000000 9
b00000000000000000000000000000000 :
b00000000000000000000000000000000 ;
b00000000000000000000000000000000 <
b00000000000000000000000000000000 =
b00000000000000000000000000000000 >
b00000000000000000000000000000000 ?
b00000000000000000000000000000000 @
b00000000000000000000000000000000 A
b00000000000000000000000000000000 B
b00000000000000000000000000000000 C
b00000000000000000000000000000000 D
0E
b000 F
0G
0H
0I
b000 J
b00000000000000000000000000000000 K
b00000 L
b00000 M
b00000 N
b00000000000000000000000000000000 O
b00000000000000000000000000000000 P
b00000000000000000000000000000000 Q
b0000000 R
b000 S
0T
1U
b00000000000000000000000000000000 V
b00000000000000000000000000000000 W
b00000000000000000000000000000000 X
b00000000000000000000000000000100 Y
b00000000000000000000000000000000 Z
b00000000000000000000000000000100 [
b00000000000000000000000000100000 \
b00000000000000000000000000000101 ]
#1
b00000000000000000000000000100000 #
b00001111111100000000001100010011 D
1G
1I
b00000000000000000000000011111111 K
b11111 M
b00110 N
b00000000000000000000000011111111 P
b00000000000000000000000011111111 Q
b0010011 R
1T
b00000000000000000000000011111111 Z
#2
0T
#3
b00000000000000000000000011111111 *
1T
#4
0T
#5
1T
#6
0T
#7
1T
#8
0T
0U
#9
b00000000000000000000010100010011 D
1H
b00000000000000000000000000000000 K
b00000 M
b01010 N
b00000000000000000000000000000000 P
b00000000000000000000000000000000 Q
1T
b00000000000000000000000000000100 W
b00000000000000000000000000001000 Y
b00000000000000000000000000000100 Z
b00000000000000000000000000001000 [
#10
0T
#11
b00000000000000000000010110010011 D
b01011 N
1T
b00000000000000000000000000001000 W
b00000000000000000000000000001100 Y
b00000000000000000000000000001000 Z
b00000000000000000000000000001100 [
#12
0T
#13
b00000000000001011000010100010011 D
b01011 L
b01010 N
1T
b00000000000000000000000000001100 W
b00000000000000000000000000010000 Y
b00000000000000000000000000001100 Z
b00000000000000000000000000010000 [
#14
0T
#15
b00000000000101011000010110010011 D
0H
b00000000000000000000000000000001 K
b00001 M
b01011 N
b00000000000000000000000000000001 P
b00000000000000000000000000000001 Q
1T
b00000000000000000000000000010000 W
b00000000000000000000000000010100 Y
b00000000000000000000000000010001 Z
b00000000000000000000000000010100 [
#16
0T
#17
b00000000000000000000000000000001 /
b11111110011001011001110011100011 D
1E
0G
0I
b001 J
b11111111111111111111111111111000 K
b00110 M
b11001 N
b00000000000000000000000000000001 O
b00000000000000000000000011111111 P
b00000000000000000000000100000000 Q
b1100011 R
b001 S
1T
b00000000000000000000000000010100 W
b00000000000000000000000011111111 X
b00000000000000000000000000011000 Y
b00000000000000000000000000001100 Z
b00000000000000000000000000001100 [
#18
0T
#19
b00000000000001011000010100010011 D
0E
1G
1I
b000 J
b00000000000000000000000000000000 K
b00000 M
b01010 N
b00000000000000000000000000000000 P
b00000000000000000000000000000001 Q
b0010011 R
b000 S
1T
b00000000000000000000000000001100 W
b00000000000000000000000000000000 X
b00000000000000000000000000010000 Y
b00000000000000000000000000010000 [
#20
0T
#21
b00000000000000000000000000000001 .
b00000000000101011000010110010011 D
1H
b00000000000000000000000000000001 K
b00001 M
b01011 N
b00000000000000000000000000000001 P
b00000000000000000000000000000010 Q
1T
b00000000000000000000000000000001 V
b00000000000000000000000000010000 W
b00000000000000000000000000010100 Y
b00000000000000000000000000010001 Z
b00000000000000000000000000010100 [
#22
0T
#23
b00000000000000000000000000000010 /
b11111110011001011001110011100011 D
1E
0G
0H
0I
b001 J
b11111111111111111111111111111000 K
b00110 M
b11001 N
b00000000000000000000000000000010 O
b00000000000000000000000011111111 P
b00000000000000000000000100000001 Q
b1100011 R
b001 S
1T
b00000000000000000000000000010100 W
b00000000000000000000000011111111 X
b00000000000000000000000000011000 Y
b00000000000000000000000000001100 Z
b00000000000000000000000000001100 [
#24
0T
#25
b00000000000001011000010100010011 D
0E
1G
1I
b000 J
b00000000000000000000000000000000 K
b00000 M
b01010 N
b00000000000000000000000000000000 P
b00000000000000000000000000000010 Q
b0010011 R
b000 S
1T
b00000000000000000000000000001100 W
b00000000000000000000000000000000 X
b00000000000000000000000000010000 Y
b00000000000000000000000000010000 [
#26
0T
#27
b00000000000000000000000000000010 .
b00000000000101011000010110010011 D
b00000000000000000000000000000001 K
b00001 M
b01011 N
b00000000000000000000000000000001 P
b00000000000000000000000000000011 Q
1T
b00000000000000000000000000000010 V
b00000000000000000000000000010000 W
b00000000000000000000000000010100 Y
b00000000000000000000000000010001 Z
b00000000000000000000000000010100 [
#28
0T
#29
b00000000000000000000000000000011 /
b11111110011001011001110011100011 D
1E
0G
0I
b001 J
b11111111111111111111111111111000 K
b00110 M
b11001 N
b00000000000000000000000000000011 O
b00000000000000000000000011111111 P
b00000000000000000000000100000010 Q
b1100011 R
b001 S
1T
b00000000000000000000000000010100 W
b00000000000000000000000011111111 X
b00000000000000000000000000011000 Y
b00000000000000000000000000001100 Z
b00000000000000000000000000001100 [
#30
0T
#31
b00000000000001011000010100010011 D
0E
1G
1I
b000 J
b00000000000000000000000000000000 K
b00000 M
b01010 N
b00000000000000000000000000000000 P
b00000000000000000000000000000011 Q
b0010011 R
b000 S
1T
b00000000000000000000000000001100 W
b00000000000000000000000000000000 X
b00000000000000000000000000010000 Y
b00000000000000000000000000010000 [
#32
0T
#33
b00000000000000000000000000000011 .
b00000000000101011000010110010011 D
b00000000000000000000000000000001 K
b00001 M
b01011 N
b00000000000000000000000000000001 P
b00000000000000000000000000000100 Q
1T
b00000000000000000000000000000011 V
b00000000000000000000000000010000 W
b00000000000000000000000000010100 Y
b00000000000000000000000000010001 Z
b00000000000000000000000000010100 [
#34
0T
#35
b00000000000000000000000000000100 /
b11111110011001011001110011100011 D
1E
0G
0I
b001 J
b11111111111111111111111111111000 K
b00110 M
b11001 N
b00000000000000000000000000000100 O
b00000000000000000000000011111111 P
b00000000000000000000000100000011 Q
b1100011 R
b001 S
1T
b00000000000000000000000000010100 W
b00000000000000000000000011111111 X
b00000000000000000000000000011000 Y
b00000000000000000000000000001100 Z
b00000000000000000000000000001100 [
#36
0T
#37
b00000000000001011000010100010011 D
0E
1G
1I
b000 J
b00000000000000000000000000000000 K
b00000 M
b01010 N
b00000000000000000000000000000000 P
b00000000000000000000000000000100 Q
b0010011 R
b000 S
1T
b00000000000000000000000000001100 W
b00000000000000000000000000000000 X
b00000000000000000000000000010000 Y
b00000000000000000000000000010000 [
#38
0T
#39
b00000000000000000000000000000100 .
b00000000000101011000010110010011 D
b00000000000000000000000000000001 K
b00001 M
b01011 N
b00000000000000000000000000000001 P
b00000000000000000000000000000101 Q
1T
b00000000000000000000000000000100 V
b00000000000000000000000000010000 W
b00000000000000000000000000010100 Y
b00000000000000000000000000010001 Z
b00000000000000000000000000010100 [
#40
0T
#41
b00000000000000000000000000000101 /
b11111110011001011001110011100011 D
1E
0G
0I
b001 J
b11111111111111111111111111111000 K
b00110 M
b11001 N
b00000000000000000000000000000101 O
b00000000000000000000000011111111 P
b00000000000000000000000100000100 Q
b1100011 R
b001 S
1T
b00000000000000000000000000010100 W
b00000000000000000000000011111111 X
b00000000000000000000000000011000 Y
b00000000000000000000000000001100 Z
b00000000000000000000000000001100 [
#42
0T
#43
b00000000000001011000010100010011 D
0E
1G
1I
b000 J
b00000000000000000000000000000000 K
b00000 M
b01010 N
b00000000000000000000000000000000 P
b00000000000000000000000000000101 Q
b0010011 R
b000 S
1T
b00000000000000000000000000001100 W
b00000000000000000000000000000000 X
b00000000000000000000000000010000 Y
b00000000000000000000000000010000 [
#44
0T
#45
b00000000000000000000000000000101 .
b00000000000101011000010110010011 D
b00000000000000000000000000000001 K
b00001 M
b01011 N
b00000000000000000000000000000001 P
b00000000000000000000000000000110 Q
1T
b00000000000000000000000000000101 V
b00000000000000000000000000010000 W
b00000000000000000000000000010100 Y
b00000000000000000000000000010001 Z
b00000000000000000000000000010100 [
#46
0T
#47
b00000000000000000000000000000110 /
b11111110011001011001110011100011 D
1E
0G
0I
b001 J
b11111111111111111111111111111000 K
b00110 M
b11001 N
b00000000000000000000000000000110 O
b00000000000000000000000011111111 P
b00000000000000000000000100000101 Q
b1100011 R
b001 S
1T
b00000000000000000000000000010100 W
b00000000000000000000000011111111 X
b00000000000000000000000000011000 Y
b00000000000000000000000000001100 Z
b00000000000000000000000000001100 [
#48
0T
#49
b00000000000001011000010100010011 D
0E
1G
1I
b000 J
b00000000000000000000000000000000 K
b00000 M
b01010 N
b00000000000000000000000000000000 P
b00000000000000000000000000000110 Q
b0010011 R
b000 S
1T
b00000000000000000000000000001100 W
b00000000000000000000000000000000 X
b00000000000000000000000000010000 Y
b00000000000000000000000000010000 [
#50
0T
#51
b00000000000000000000000000000110 .
b00000000000101011000010110010011 D
b00000000000000000000000000000001 K
b00001 M
b01011 N
b00000000000000000000000000000001 P
b00000000000000000000000000000111 Q
1T
b00000000000000000000000000000110 V
b00000000000000000000000000010000 W
b00000000000000000000000000010100 Y
b00000000000000000000000000010001 Z
b00000000000000000000000000010100 [
#52
0T
#53
b00000000000000000000000000000111 /
b11111110011001011001110011100011 D
1E
0G
0I
b001 J
b11111111111111111111111111111000 K
b00110 M
b11001 N
b00000000000000000000000000000111 O
b00000000000000000000000011111111 P
b00000000000000000000000100000110 Q
b1100011 R
b001 S
1T
b00000000000000000000000000010100 W
b00000000000000000000000011111111 X
b00000000000000000000000000011000 Y
b00000000000000000000000000001100 Z
b00000000000000000000000000001100 [
#54
0T
#55
b00000000000001011000010100010011 D
0E
1G
1I
b000 J
b00000000000000000000000000000000 K
b00000 M
b01010 N
b00000000000000000000000000000000 P
b00000000000000000000000000000111 Q
b0010011 R
b000 S
1T
b00000000000000000000000000001100 W
b00000000000000000000000000000000 X
b00000000000000000000000000010000 Y
b00000000000000000000000000010000 [
#56
0T
#57
b00000000000000000000000000000111 .
b00000000000101011000010110010011 D
b00000000000000000000000000000001 K
b00001 M
b01011 N
b00000000000000000000000000000001 P
b00000000000000000000000000001000 Q
1T
b00000000000000000000000000000111 V
b00000000000000000000000000010000 W
b00000000000000000000000000010100 Y
b00000000000000000000000000010001 Z
b00000000000000000000000000010100 [
#58
0T
#59
b00000000000000000000000000001000 /
b11111110011001011001110011100011 D
1E
0G
0I
b001 J
b11111111111111111111111111111000 K
b00110 M
b11001 N
b00000000000000000000000000001000 O
b00000000000000000000000011111111 P
b00000000000000000000000100000111 Q
b1100011 R
b001 S
1T
b00000000000000000000000000010100 W
b00000000000000000000000011111111 X
b00000000000000000000000000011000 Y
b00000000000000000000000000001100 Z
b00000000000000000000000000001100 [
#60
0T
#61
b00000000000001011000010100010011 D
0E
1G
1I
b000 J
b00000000000000000000000000000000 K
b00000 M
b01010 N
b00000000000000000000000000000000 P
b00000000000000000000000000001000 Q
b0010011 R
b000 S
1T
b00000000000000000000000000001100 W
b00000000000000000000000000000000 X
b00000000000000000000000000010000 Y
b00000000000000000000000000010000 [
#62
0T
#63
b00000000000000000000000000001000 .
b00000000000101011000010110010011 D
b00000000000000000000000000000001 K
b00001 M
b01011 N
b00000000000000000000000000000001 P
b00000000000000000000000000001001 Q
1T
b00000000000000000000000000001000 V
b00000000000000000000000000010000 W
b00000000000000000000000000010100 Y
b00000000000000000000000000010001 Z
b00000000000000000000000000010100 [
#64
0T
#65
b00000000000000000000000000001001 /
b11111110011001011001110011100011 D
1E
0G
0I
b001 J
b11111111111111111111111111111000 K
b00110 M
b11001 N
b00000000000000000000000000001001 O
b00000000000000000000000011111111 P
b00000000000000000000000100001000 Q
b1100011 R
b001 S
1T
b00000000000000000000000000010100 W
b00000000000000000000000011111111 X
b00000000000000000000000000011000 Y
b00000000000000000000000000001100 Z
b00000000000000000000000000001100 [
#66
0T
#67
b00000000000001011000010100010011 D
0E
1G
1I
b000 J
b00000000000000000000000000000000 K
b00000 M
b01010 N
b00000000000000000000000000000000 P
b00000000000000000000000000001001 Q
b0010011 R
b000 S
1T
b00000000000000000000000000001100 W
b00000000000000000000000000000000 X
b00000000000000000000000000010000 Y
b00000000000000000000000000010000 [
#68
0T
#69
b00000000000000000000000000001001 .
b00000000000101011000010110010011 D
b00000000000000000000000000000001 K
b00001 M
b01011 N
b00000000000000000000000000000001 P
b00000000000000000000000000001010 Q
1T
b00000000000000000000000000001001 V
b00000000000000000000000000010000 W
b00000000000000000000000000010100 Y
b00000000000000000000000000010001 Z
b00000000000000000000000000010100 [
#70
0T
#71
b00000000000000000000000000001010 /
b11111110011001011001110011100011 D
1E
0G
0I
b001 J
b11111111111111111111111111111000 K
b00110 M
b11001 N
b00000000000000000000000000001010 O
b00000000000000000000000011111111 P
b00000000000000000000000100001001 Q
b1100011 R
b001 S
1T
b00000000000000000000000000010100 W
b00000000000000000000000011111111 X
b00000000000000000000000000011000 Y
b00000000000000000000000000001100 Z
b00000000000000000000000000001100 [
#72
0T
#73
b00000000000001011000010100010011 D
0E
1G
1I
b000 J
b00000000000000000000000000000000 K
b00000 M
b01010 N
b00000000000000000000000000000000 P
b00000000000000000000000000001010 Q
b0010011 R
b000 S
1T
b00000000000000000000000000001100 W
b00000000000000000000000000000000 X
b00000000000000000000000000010000 Y
b00000000000000000000000000010000 [
#74
0T
#75
b00000000000000000000000000001010 .
b00000000000101011000010110010011 D
b00000000000000000000000000000001 K
b00001 M
b01011 N
b00000000000000000000000000000001 P
b00000000000000000000000000001011 Q
1T
b00000000000000000000000000001010 V
b00000000000000000000000000010000 W
b00000000000000000000000000010100 Y
b00000000000000000000000000010001 Z
b00000000000000000000000000010100 [
#76
0T
#77
b00000000000000000000000000001011 /
b11111110011001011001110011100011 D
1E
0G
0I
b001 J
b11111111111111111111111111111000 K
b00110 M
b11001 N
b00000000000000000000000000001011 O
b00000000000000000000000011111111 P
b00000000000000000000000100001010 Q
b1100011 R
b001 S
1T
b00000000000000000000000000010100 W
b00000000000000000000000011111111 X
b00000000000000000000000000011000 Y
b00000000000000000000000000001100 Z
b00000000000000000000000000001100 [
#78
0T
#79
b00000000000001011000010100010011 D
0E
1G
1I
b000 J
b00000000000000000000000000000000 K
b00000 M
b01010 N
b00000000000000000000000000000000 P
b00000000000000000000000000001011 Q
b0010011 R
b000 S
1T
b00000000000000000000000000001100 W
b00000000000000000000000000000000 X
b00000000000000000000000000010000 Y
b00000000000000000000000000010000 [
#80
0T
#81
b00000000000000000000000000001011 .
b00000000000101011000010110010011 D
b00000000000000000000000000000001 K
b00001 M
b01011 N
b00000000000000000000000000000001 P
b00000000000000000000000000001100 Q
1T
b00000000000000000000000000001011 V
b00000000000000000000000000010000 W
b00000000000000000000000000010100 Y
b00000000000000000000000000010001 Z
b00000000000000000000000000010100 [
#82
0T
#83
b00000000000000000000000000001100 /
b11111110011001011001110011100011 D
1E
0G
0I
b001 J
b11111111111111111111111111111000 K
b00110 M
b11001 N
b00000000000000000000000000001100 O
b00000000000000000000000011111111 P
b00000000000000000000000100001011 Q
b1100011 R
b001 S
1T
b00000000000000000000000000010100 W
b00000000000000000000000011111111 X
b00000000000000000000000000011000 Y
b00000000000000000000000000001100 Z
b00000000000000000000000000001100 [
#84
0T
#85
b00000000000001011000010100010011 D
0E
1G
1I
b000 J
b00000000000000000000000000000000 K
b00000 M
b01010 N
b00000000000000000000000000000000 P
b00000000000000000000000000001100 Q
b0010011 R
b000 S
1T
b00000000000000000000000000001100 W
b00000000000000000000000000000000 X
b00000000000000000000000000010000 Y
b00000000000000000000000000010000 [
#86
0T
#87
b00000000000000000000000000001100 .
b00000000000101011000010110010011 D
b00000000000000000000000000000001 K
b00001 M
b01011 N
b00000000000000000000000000000001 P
b00000000000000000000000000001101 Q
1T
b00000000000000000000000000001100 V
b00000000000000000000000000010000 W
b00000000000000000000000000010100 Y
b00000000000000000000000000010001 Z
b00000000000000000000000000010100 [
#88
0T
#89
b00000000000000000000000000001101 /
b11111110011001011001110011100011 D
1E
0G
0I
b001 J
b11111111111111111111111111111000 K
b00110 M
b11001 N
b00000000000000000000000000001101 O
b00000000000000000000000011111111 P
b00000000000000000000000100001100 Q
b1100011 R
b001 S
1T
b00000000000000000000000000010100 W
b00000000000000000000000011111111 X
b00000000000000000000000000011000 Y
b00000000000000000000000000001100 Z
b00000000000000000000000000001100 [
#90
0T
